wxbinder/__init__.py
wxbinder-0.0.0.dist-info/AUTHORS
wxbinder-0.0.0.dist-info/LICENSE
wxbinder-0.0.0.dist-info/METADATA
wxbinder-0.0.0.dist-info/WHEEL
wxbinder-0.0.0.dist-info/pbr.json
wxbinder-0.0.0.dist-info/top_level.txt
wxbinder-0.0.0.dist-info/RECORD
